disposable_email_score/__init__.py
disposable_email_score/config.py
disposable_email_score/core.py
disposable_email_score/models.py
disposable_email_score/signals.py
disposable_email_score/data/allow_email_list.conf
disposable_email_score/data/email_block_list.conf
disposable_email_score-0.1.1.dist-info/METADATA
disposable_email_score-0.1.1.dist-info/WHEEL
disposable_email_score-0.1.1.dist-info/licenses/LICENSE
disposable_email_score-0.1.1.dist-info/RECORD
