Metadata-Version: 2.4
Name: disposable-email-score
Version: 0.1.1
Summary: A risk-scoring engine for email signups.
Project-URL: Homepage, https://github.com/Harshit28j/disposable-email-score
Project-URL: Sponsor, https://github.com/sponsors/Harshit28j
Author-email: Harshit <harshitjain0562@gmail.com>
License-Expression: MIT
License-File: LICENSE
Keywords: abuse,disposable,email,fraud,risk,score,security,signup,spam,temporary,validation
Classifier: Development Status :: 4 - Beta
Classifier: Intended Audience :: Developers
Classifier: License :: OSI Approved :: MIT License
Classifier: Programming Language :: Python :: 3
Classifier: Programming Language :: Python :: 3.8
Classifier: Programming Language :: Python :: 3.9
Classifier: Programming Language :: Python :: 3.10
Classifier: Programming Language :: Python :: 3.11
Classifier: Programming Language :: Python :: 3.12
Requires-Python: >=3.8
Requires-Dist: dnspython>=2.0.0
Requires-Dist: pydantic>=2.0.0
Provides-Extra: dev
Requires-Dist: pytest-cov>=4.0.0; extra == 'dev'
Requires-Dist: pytest>=7.0.0; extra == 'dev'
Requires-Dist: ruff>=0.1.0; extra == 'dev'
